{
  "passes": {
    "ex01": [
      {
        "user": "urmsandeep-test-01",
        "ts": "2026-04-22T08:32:34.554686+00:00"
      },
      {
        "user": "urmsandeep",
        "ts": "2026-04-22T11:03:19.250215+00:00"
      },
      {
        "user": "Vishnureddy910",
        "ts": "2026-04-22T11:03:19.250215+00:00"
      },
      {
        "user": "Akif-ka",
        "ts": "2026-04-22T11:08:46.230905+00:00"
      },
      {
        "user": "akshay-820",
        "ts": "2026-04-22T11:10:37.118457+00:00"
      },
      {
        "user": "Adithya-Vipin",
        "ts": "2026-04-22T11:14:29.584336+00:00"
      },
      {
        "user": "BKSHEERAJ",
        "ts": "2026-04-22T11:14:29.584336+00:00"
      },
      {
        "user": "chethanataltaje",
        "ts": "2026-04-22T11:29:56.383489+00:00"
      }
    ]
  },
  "attempts": {
    "urmsandeep-test-01|ex01": 1,
    "urmsandeep-test-01|ex02": 124,
    "urmsandeep-test-01|ex03": 124,
    "urmsandeep-test-01|ex04": 124,
    "urmsandeep-test-01|ex05": 124,
    "urmsandeep-test-01|ex06": 124,
    "urmsandeep-test-01|ex07": 124,
    "urmsandeep-test-01|ex08": 124,
    "urmsandeep-test-01|ex09": 124,
    "urmsandeep-test-01|ex10": 124,
    "urmsandeep|ex01": 7,
    "urmsandeep|ex02": 124,
    "urmsandeep|ex03": 124,
    "urmsandeep|ex04": 124,
    "urmsandeep|ex05": 124,
    "urmsandeep|ex06": 124,
    "urmsandeep|ex07": 124,
    "urmsandeep|ex08": 124,
    "urmsandeep|ex09": 124,
    "urmsandeep|ex10": 124,
    "afrinmtp|ex01": 120,
    "afrinmtp|ex02": 120,
    "afrinmtp|ex03": 120,
    "afrinmtp|ex04": 120,
    "afrinmtp|ex05": 120,
    "afrinmtp|ex06": 120,
    "afrinmtp|ex07": 120,
    "afrinmtp|ex08": 120,
    "afrinmtp|ex09": 120,
    "afrinmtp|ex10": 120,
    "VIGHNESH002|ex01": 119,
    "VIGHNESH002|ex02": 119,
    "VIGHNESH002|ex03": 119,
    "VIGHNESH002|ex04": 119,
    "VIGHNESH002|ex05": 119,
    "VIGHNESH002|ex06": 119,
    "VIGHNESH002|ex07": 119,
    "VIGHNESH002|ex08": 119,
    "VIGHNESH002|ex09": 119,
    "VIGHNESH002|ex10": 119,
    "amriththejas|ex01": 118,
    "amriththejas|ex02": 118,
    "amriththejas|ex03": 118,
    "amriththejas|ex04": 118,
    "amriththejas|ex05": 118,
    "amriththejas|ex06": 118,
    "amriththejas|ex07": 118,
    "amriththejas|ex08": 118,
    "amriththejas|ex09": 118,
    "amriththejas|ex10": 118,
    "Vishnureddy910|ex02": 117,
    "Vishnureddy910|ex03": 117,
    "Vishnureddy910|ex04": 117,
    "Vishnureddy910|ex05": 117,
    "Vishnureddy910|ex06": 117,
    "Vishnureddy910|ex07": 117,
    "Vishnureddy910|ex08": 117,
    "Vishnureddy910|ex09": 117,
    "Vishnureddy910|ex10": 117,
    "Adithya-Vipin|ex01": 3,
    "Adithya-Vipin|ex02": 116,
    "Adithya-Vipin|ex03": 116,
    "Adithya-Vipin|ex04": 116,
    "Adithya-Vipin|ex05": 116,
    "Adithya-Vipin|ex06": 116,
    "Adithya-Vipin|ex07": 116,
    "Adithya-Vipin|ex08": 116,
    "Adithya-Vipin|ex09": 116,
    "Adithya-Vipin|ex10": 116,
    "Akif-ka|ex02": 115,
    "Akif-ka|ex03": 115,
    "Akif-ka|ex04": 115,
    "Akif-ka|ex05": 115,
    "Akif-ka|ex06": 115,
    "Akif-ka|ex07": 115,
    "Akif-ka|ex08": 115,
    "Akif-ka|ex09": 115,
    "Akif-ka|ex10": 115,
    "akshay-820|ex02": 114,
    "akshay-820|ex03": 114,
    "akshay-820|ex04": 114,
    "akshay-820|ex05": 114,
    "akshay-820|ex06": 114,
    "akshay-820|ex07": 114,
    "akshay-820|ex08": 114,
    "akshay-820|ex09": 114,
    "akshay-820|ex10": 114,
    "BKSHEERAJ|ex02": 113,
    "BKSHEERAJ|ex03": 113,
    "BKSHEERAJ|ex04": 113,
    "BKSHEERAJ|ex05": 113,
    "BKSHEERAJ|ex06": 113,
    "BKSHEERAJ|ex07": 113,
    "BKSHEERAJ|ex08": 113,
    "BKSHEERAJ|ex09": 113,
    "BKSHEERAJ|ex10": 113,
    "chethanataltaje|ex02": 112,
    "chethanataltaje|ex03": 112,
    "chethanataltaje|ex04": 112,
    "chethanataltaje|ex05": 112,
    "chethanataltaje|ex06": 112,
    "chethanataltaje|ex07": 112,
    "chethanataltaje|ex08": 112,
    "chethanataltaje|ex09": 112,
    "chethanataltaje|ex10": 112
  }
}