{
  "passes": {
    "ex01": [
      {
        "user": "urmsandeep-test-01",
        "ts": "2026-04-22T08:32:34.554686+00:00"
      },
      {
        "user": "urmsandeep",
        "ts": "2026-04-22T11:03:19.250215+00:00"
      },
      {
        "user": "Vishnureddy910",
        "ts": "2026-04-22T11:03:19.250215+00:00"
      },
      {
        "user": "Akif-ka",
        "ts": "2026-04-22T11:08:46.230905+00:00"
      },
      {
        "user": "akshay-820",
        "ts": "2026-04-22T11:10:37.118457+00:00"
      },
      {
        "user": "Adithya-Vipin",
        "ts": "2026-04-22T11:14:29.584336+00:00"
      },
      {
        "user": "BKSHEERAJ",
        "ts": "2026-04-22T11:14:29.584336+00:00"
      },
      {
        "user": "chethanataltaje",
        "ts": "2026-04-22T11:29:56.383489+00:00"
      },
      {
        "user": "batulhs",
        "ts": "2026-04-30T11:23:50.878904+00:00"
      }
    ]
  },
  "attempts": {
    "urmsandeep-test-01|ex01": 1,
    "urmsandeep-test-01|ex02": 526,
    "urmsandeep-test-01|ex03": 526,
    "urmsandeep-test-01|ex04": 526,
    "urmsandeep-test-01|ex05": 526,
    "urmsandeep-test-01|ex06": 526,
    "urmsandeep-test-01|ex07": 526,
    "urmsandeep-test-01|ex08": 526,
    "urmsandeep-test-01|ex09": 526,
    "urmsandeep-test-01|ex10": 526,
    "urmsandeep|ex01": 7,
    "urmsandeep|ex02": 526,
    "urmsandeep|ex03": 526,
    "urmsandeep|ex04": 526,
    "urmsandeep|ex05": 526,
    "urmsandeep|ex06": 526,
    "urmsandeep|ex07": 526,
    "urmsandeep|ex08": 526,
    "urmsandeep|ex09": 526,
    "urmsandeep|ex10": 526,
    "afrinmtp|ex01": 522,
    "afrinmtp|ex02": 522,
    "afrinmtp|ex03": 522,
    "afrinmtp|ex04": 522,
    "afrinmtp|ex05": 522,
    "afrinmtp|ex06": 522,
    "afrinmtp|ex07": 522,
    "afrinmtp|ex08": 522,
    "afrinmtp|ex09": 522,
    "afrinmtp|ex10": 522,
    "VIGHNESH002|ex01": 521,
    "VIGHNESH002|ex02": 521,
    "VIGHNESH002|ex03": 521,
    "VIGHNESH002|ex04": 521,
    "VIGHNESH002|ex05": 521,
    "VIGHNESH002|ex06": 521,
    "VIGHNESH002|ex07": 521,
    "VIGHNESH002|ex08": 521,
    "VIGHNESH002|ex09": 521,
    "VIGHNESH002|ex10": 521,
    "amriththejas|ex01": 520,
    "amriththejas|ex02": 520,
    "amriththejas|ex03": 520,
    "amriththejas|ex04": 520,
    "amriththejas|ex05": 520,
    "amriththejas|ex06": 520,
    "amriththejas|ex07": 520,
    "amriththejas|ex08": 520,
    "amriththejas|ex09": 520,
    "amriththejas|ex10": 520,
    "Vishnureddy910|ex02": 519,
    "Vishnureddy910|ex03": 519,
    "Vishnureddy910|ex04": 519,
    "Vishnureddy910|ex05": 519,
    "Vishnureddy910|ex06": 519,
    "Vishnureddy910|ex07": 519,
    "Vishnureddy910|ex08": 519,
    "Vishnureddy910|ex09": 519,
    "Vishnureddy910|ex10": 519,
    "Adithya-Vipin|ex01": 3,
    "Adithya-Vipin|ex02": 518,
    "Adithya-Vipin|ex03": 518,
    "Adithya-Vipin|ex04": 518,
    "Adithya-Vipin|ex05": 518,
    "Adithya-Vipin|ex06": 518,
    "Adithya-Vipin|ex07": 518,
    "Adithya-Vipin|ex08": 518,
    "Adithya-Vipin|ex09": 518,
    "Adithya-Vipin|ex10": 518,
    "Akif-ka|ex02": 517,
    "Akif-ka|ex03": 517,
    "Akif-ka|ex04": 517,
    "Akif-ka|ex05": 517,
    "Akif-ka|ex06": 517,
    "Akif-ka|ex07": 517,
    "Akif-ka|ex08": 517,
    "Akif-ka|ex09": 517,
    "Akif-ka|ex10": 517,
    "akshay-820|ex02": 516,
    "akshay-820|ex03": 516,
    "akshay-820|ex04": 516,
    "akshay-820|ex05": 516,
    "akshay-820|ex06": 516,
    "akshay-820|ex07": 516,
    "akshay-820|ex08": 516,
    "akshay-820|ex09": 516,
    "akshay-820|ex10": 516,
    "BKSHEERAJ|ex02": 515,
    "BKSHEERAJ|ex03": 515,
    "BKSHEERAJ|ex04": 515,
    "BKSHEERAJ|ex05": 515,
    "BKSHEERAJ|ex06": 515,
    "BKSHEERAJ|ex07": 515,
    "BKSHEERAJ|ex08": 515,
    "BKSHEERAJ|ex09": 515,
    "BKSHEERAJ|ex10": 515,
    "chethanataltaje|ex02": 514,
    "chethanataltaje|ex03": 514,
    "chethanataltaje|ex04": 514,
    "chethanataltaje|ex05": 514,
    "chethanataltaje|ex06": 514,
    "chethanataltaje|ex07": 514,
    "chethanataltaje|ex08": 514,
    "chethanataltaje|ex09": 514,
    "chethanataltaje|ex10": 514,
    "batulhs|ex02": 1,
    "batulhs|ex03": 1,
    "batulhs|ex04": 1,
    "batulhs|ex05": 1,
    "batulhs|ex06": 1,
    "batulhs|ex07": 1,
    "batulhs|ex08": 1,
    "batulhs|ex09": 1,
    "batulhs|ex10": 1
  }
}